LICENSE
README
config.json.in
configure
configure.ac
setup.py
badic/Automaton.h
badic/__init__.py
badic/automataC.c
badic/automataC.h
badic/beta_adic.pxd
badic/beta_adic.pyx
badic/cautomata.pxd
badic/cautomata.pyx
badic/cautomata_generators.py
badic/complexe.c
badic/complexe.h
badic/density.pyx
badic/draw.c
badic/draw.h
badic/misc.pyx
badic/miscellanious.c
badic/miscellanious.h
badic/relations.c
badic/relations.h
badic/turing.c
badic/turing.py