Metadata-Version: 2.1
Name: badic
Version: 0.1.0
Summary: Beta-adics and automata tools
Home-page: https://gitlab.com/mercatp/badic
Author: Paul Mercat, Dominique Benielli
Author-email: paul.mercat@univ-amu.fr
License: GPLv3+
Keywords: SageMath beta-adic automata multidimensional continued fraction algorithms
Classifier: Development Status :: 4 - Beta
Classifier: Intended Audience :: Science/Research
Classifier: Topic :: Software Development :: Build Tools
Classifier: Topic :: Scientific/Engineering :: Mathematics
Classifier: License :: OSI Approved :: GNU General Public License v3 or later (GPLv3+)
Classifier: Programming Language :: Python :: 2.7
Classifier: Programming Language :: Python :: 3
Classifier: Programming Language :: Cython
Classifier: Programming Language :: C
License-File: LICENSE
